README.md
setup.py
IOT3/__init__.py
IOT3ApiClient.egg-info/PKG-INFO
IOT3ApiClient.egg-info/SOURCES.txt
IOT3ApiClient.egg-info/dependency_links.txt
IOT3ApiClient.egg-info/top_level.txt
certifi/__init__.py
certifi/__main__.py
certifi/core.py
charset_normalizer/__init__.py
charset_normalizer/api.py
charset_normalizer/cd.py
charset_normalizer/constant.py
charset_normalizer/legacy.py
charset_normalizer/md.py
charset_normalizer/models.py
charset_normalizer/utils.py
charset_normalizer/version.py
charset_normalizer/assets/__init__.py
charset_normalizer/cli/__init__.py
charset_normalizer/cli/normalizer.py
idna/__init__.py
idna/codec.py
idna/compat.py
idna/core.py
idna/idnadata.py
idna/intranges.py
idna/package_data.py
idna/uts46data.py
requests/__init__.py
requests/__version__.py
requests/_internal_utils.py
requests/adapters.py
requests/api.py
requests/auth.py
requests/certs.py
requests/compat.py
requests/cookies.py
requests/exceptions.py
requests/help.py
requests/hooks.py
requests/models.py
requests/packages.py
requests/sessions.py
requests/status_codes.py
requests/structures.py
requests/utils.py
urllib3/__init__.py
urllib3/_collections.py
urllib3/_version.py
urllib3/connection.py
urllib3/connectionpool.py
urllib3/exceptions.py
urllib3/fields.py
urllib3/filepost.py
urllib3/poolmanager.py
urllib3/request.py
urllib3/response.py
urllib3/contrib/__init__.py
urllib3/contrib/_appengine_environ.py
urllib3/contrib/appengine.py
urllib3/contrib/ntlmpool.py
urllib3/contrib/pyopenssl.py
urllib3/contrib/securetransport.py
urllib3/contrib/socks.py
urllib3/contrib/_securetransport/__init__.py
urllib3/contrib/_securetransport/bindings.py
urllib3/contrib/_securetransport/low_level.py
urllib3/packages/__init__.py
urllib3/packages/six.py
urllib3/packages/backports/__init__.py
urllib3/packages/backports/makefile.py
urllib3/packages/ssl_match_hostname/__init__.py
urllib3/packages/ssl_match_hostname/_implementation.py
urllib3/util/__init__.py
urllib3/util/connection.py
urllib3/util/proxy.py
urllib3/util/queue.py
urllib3/util/request.py
urllib3/util/response.py
urllib3/util/retry.py
urllib3/util/ssl_.py
urllib3/util/ssltransport.py
